codeshift/__init__.py
codeshift/analyzer/__init__.py
codeshift/analyzer/risk_assessor.py
codeshift/cli/__init__.py
codeshift/cli/main.py
codeshift/cli/package_manager.py
codeshift/cli/quota.py
codeshift/cli/commands/__init__.py
codeshift/cli/commands/apply.py
codeshift/cli/commands/auth.py
codeshift/cli/commands/diff.py
codeshift/cli/commands/scan.py
codeshift/cli/commands/upgrade.py
codeshift/cli/commands/upgrade_all.py
codeshift/knowledge/__init__.py
codeshift/knowledge/cache.py
codeshift/knowledge/generator.py
codeshift/knowledge/models.py
codeshift/knowledge/parser.py
codeshift/knowledge/sources.py
codeshift/knowledge_base/__init__.py
codeshift/knowledge_base/loader.py
codeshift/knowledge_base/models.py
codeshift/knowledge_base/libraries/aiohttp.yaml
codeshift/knowledge_base/libraries/attrs.yaml
codeshift/knowledge_base/libraries/celery.yaml
codeshift/knowledge_base/libraries/click.yaml
codeshift/knowledge_base/libraries/django.yaml
codeshift/knowledge_base/libraries/fastapi.yaml
codeshift/knowledge_base/libraries/flask.yaml
codeshift/knowledge_base/libraries/httpx.yaml
codeshift/knowledge_base/libraries/marshmallow.yaml
codeshift/knowledge_base/libraries/numpy.yaml
codeshift/knowledge_base/libraries/pandas.yaml
codeshift/knowledge_base/libraries/pydantic.yaml
codeshift/knowledge_base/libraries/pytest.yaml
codeshift/knowledge_base/libraries/requests.yaml
codeshift/knowledge_base/libraries/sqlalchemy.yaml
codeshift/migrator/__init__.py
codeshift/migrator/ast_transforms.py
codeshift/migrator/engine.py
codeshift/migrator/llm_migrator.py
codeshift/migrator/transforms/__init__.py
codeshift/migrator/transforms/aiohttp_transformer.py
codeshift/migrator/transforms/attrs_transformer.py
codeshift/migrator/transforms/celery_transformer.py
codeshift/migrator/transforms/click_transformer.py
codeshift/migrator/transforms/django_transformer.py
codeshift/migrator/transforms/fastapi_transformer.py
codeshift/migrator/transforms/flask_transformer.py
codeshift-0.5.0.dist-info/licenses/LICENSE
codeshift-0.5.0.dist-info/METADATA
codeshift-0.5.0.dist-info/WHEEL
codeshift-0.5.0.dist-info/entry_points.txt
codeshift-0.5.0.dist-info/top_level.txt
codeshift-0.5.0.dist-info/RECORD
