Metadata-Version: 2.4
Name: codeshift
Version: 0.5.0
Summary: AI-powered CLI tool that migrates Python code to handle breaking dependency changes
Author: Ragab Technologies
License: MIT
Project-URL: Homepage, https://github.com/Ragab-Technologies/Codeshift
Project-URL: Repository, https://github.com/Ragab-Technologies/Codeshift
Project-URL: Issues, https://github.com/Ragab-Technologies/Codeshift/issues
Keywords: migration,dependencies,ast,refactoring,pydantic
Classifier: Development Status :: 3 - Alpha
Classifier: Intended Audience :: Developers
Classifier: License :: OSI Approved :: MIT License
Classifier: Programming Language :: Python :: 3
Classifier: Programming Language :: Python :: 3.10
Classifier: Programming Language :: Python :: 3.11
Classifier: Programming Language :: Python :: 3.12
Classifier: Topic :: Software Development :: Libraries :: Python Modules
Requires-Python: >=3.10
License-File: LICENSE
Requires-Dist: click>=8.0
Requires-Dist: libcst>=1.0
Requires-Dist: anthropic>=0.20
Requires-Dist: pyyaml>=6.0
Requires-Dist: rich>=13.0
Requires-Dist: toml>=0.10
Requires-Dist: packaging>=23.0
Requires-Dist: httpx>=0.25
Requires-Dist: black>=24.10.0
Requires-Dist: cryptography>=41.0
Requires-Dist: nox>=2025.11.12
Provides-Extra: dev
Requires-Dist: pytest>=7.0; extra == "dev"
Requires-Dist: pytest-cov>=4.0; extra == "dev"
Requires-Dist: black<25.0,>=24.0; extra == "dev"
Requires-Dist: ruff>=0.1.0; extra == "dev"
Requires-Dist: mypy>=1.0; extra == "dev"
Requires-Dist: nox>=2024.0; extra == "dev"
Requires-Dist: pre-commit>=3.6.0; extra == "dev"
Requires-Dist: types-toml>=0.10; extra == "dev"
Requires-Dist: types-PyYAML>=6.0; extra == "dev"
Dynamic: license-file
